{"id":172,"levelDefinitionId":13685,"level":{"graph":[{"x":"8","type":"8","color":"3","y":"5"},{"x":"8","type":"18","color":"-1","y":"6"},{"x":"4","type":"8","color":"3","y":"2"},{"x":"4","type":"8","color":"3","y":"9"},{"x":"2","type":"8","color":"2","y":"4"},{"x":"7","type":"9","color":"-1","y":"9"},{"x":"6","type":"8","color":"4","y":"3"},{"x":"1","type":"8","color":"3","y":"7"},{"x":"6","type":"8","color":"2","y":"10"},{"x":"6","type":"8","color":"0","y":"8"},{"x":"4","type":"8","color":"3","y":"3"},{"x":"3","type":"8","color":"4","y":"10"},{"x":"1","type":"8","color":"1","y":"5"},{"x":"3","type":"9","color":"-1","y":"8"},{"x":"8","type":"8","color":"2","y":"8"},{"x":"2","type":"9","color":"-1","y":"9"},{"x":"7","type":"9","color":"-1","y":"8"},{"x":"5","type":"8","color":"1","y":"5"},{"x":"9","type":"8","color":"0","y":"6"},{"x":"5","type":"8","color":"3","y":"7"},{"x":"8","type":"8","color":"3","y":"7"},{"x":"6","type":"8","color":"0","y":"7"},{"x":"5","type":"14","color":"-1","y":"4"},{"x":"4","type":"8","color":"4","y":"4"},{"x":"7","type":"9","color":"-1","y":"4"},{"x":"4","type":"8","color":"2","y":"8"},{"x":"7","type":"19","color":"-1","y":"6"},{"x":"4","type":"8","color":"4","y":"6"},{"x":"1","type":"8","color":"0","y":"6"},{"x":"2","type":"18","color":"-1","y":"6"},{"x":"5","type":"19","color":"-1","y":"10"},{"x":"4","type":"8","color":"0","y":"7"},{"x":"7","type":"8","color":"0","y":"7"},{"x":"7","type":"9","color":"-1","y":"3"},{"x":"5","type":"8","color":"1","y":"3"},{"x":"5","type":"4","color":"-1","y":"6"},{"x":"5","type":"18","color":"-1","y":"8"},{"x":"6","type":"8","color":"2","y":"4"},{"x":"6","type":"8","color":"0","y":"9"},{"x":"3","type":"19","color":"-1","y":"6"},{"x":"6","type":"8","color":"1","y":"6"},{"x":"2","type":"9","color":"-1","y":"3"},{"x":"3","type":"8","color":"4","y":"5"},{"x":"2","type":"8","color":"0","y":"7"},{"x":"5","type":"8","color":"1","y":"9"},{"x":"4","type":"8","color":"2","y":"10"},{"x":"7","type":"8","color":"1","y":"5"},{"x":"3","type":"9","color":"-1","y":"4"},{"x":"3","type":"8","color":"1","y":"9"},{"x":"3","type":"8","color":"3","y":"2"},{"x":"7","type":"8","color":"2","y":"10"},{"x":"2","type":"8","color":"2","y":"8"},{"x":"3","type":"8","color":"4","y":"3"},{"x":"8","type":"8","color":"2","y":"4"},{"x":"5","type":"19","color":"-1","y":"2"},{"x":"3","type":"8","color":"4","y":"7"},{"x":"7","type":"8","color":"2","y":"2"},{"x":"4","type":"8","color":"0","y":"5"},{"x":"2","type":"8","color":"0","y":"5"},{"x":"6","type":"8","color":"4","y":"2"},{"x":"6","type":"8","color":"2","y":"5"}],"mode":"wheel","gaps":"6","starlevel":[6000.0,28000.0,47000.0],"queueBubble":[],"randomColors":"5","queue":"18","graphPivot":{"y":"6","x":"5"},"wheelFrictionIndex":"2"},"version":12}